[
    {
        "id": "cagin",
        "name": "cagin cecen",
        "bio": "Full-stack Dev, Athlete, Indie Lurker",
        "email": "hello@cagin.dev",
        "avatar": "/images/authors/cagin-avatar.png",
        "links": {
            "website": "https://cagin.dev",
            "dev_to": "https://dev.to/cagdotin",
            "x": "https://x.com/cagdotin",
            "github": "https://github.com/cagdotin",
            "youtube": "https://www.youtube.com/@cagdotin",
            "linkedin": "https://linkedin.com/@caginc",
            "peerlist": "https://peerlist.com/@cagin",
            "daily_dev": "https://app.daily.dev/cagin",
            "roadmap_sh": "https://roadmap.sh/u/cagin",
            "meet": "https://cal.com/cagin",
            "onlyfans": "https://www.youtube.com/watch?v=dQw4w9WgXcQ"
        }
    }
]